{
	"problems": [
		{
			"id": 18411,
			"level": 2,
			"level_locked": 0,
			"solvable": 1,
			"title": "\u8a66\u9a13 (Exam)",
			"solved_count": 964,
			"average_try": 1.1836
		},
		{
			"id": 14038,
			"level": 2,
			"level_locked": 0,
			"solvable": 1,
			"title": "Tournament Selection",
			"solved_count": 1110,
			"average_try": 1.5036
		},
		{
			"id": 25462,
			"level": 20,
			"level_locked": 0,
			"solvable": 1,
			"title": "Inverzije",
			"solved_count": 6,
			"average_try": 1
		},
		{
			"id": 19602,
			"level": 2,
			"level_locked": 0,
			"solvable": 1,
			"title": "Dog Treats",
			"solved_count": 1137,
			"average_try": 1.1935
		},
		{
			"id": 17081,
			"level": 19,
			"level_locked": 0,
			"solvable": 1,
			"title": "RPG Extreme",
			"solved_count": 244,
			"average_try": 4.1066
		},
		{
			"id": 15000,
			"level": 2,
			"level_locked": 0,
			"solvable": 1,
			"title": "CAPS",
			"solved_count": 1220,
			"average_try": 1.2885
		},
		{
			"id": 13597,
			"level": 2,
			"level_locked": 0,
			"solvable": 1,
			"title": "Tri-du",
			"solved_count": 1247,
			"average_try": 1.1059
		},
		{
			"id": 16017,
			"level": 2,
			"level_locked": 0,
			"solvable": 1,
			"title": "Telemarketer or not?",
			"solved_count": 1144,
			"average_try": 1.4519
		},
		{
			"id": 21598,
			"level": 1,
			"level_locked": 0,
			"solvable": 1,
			"title": "SciComLove",
			"solved_count": 1166,
			"average_try": 1.1278
		},
		{
			"id": 15059,
			"level": 2,
			"level_locked": 0,
			"solvable": 1,
			"title": "Hard choice",
			"solved_count": 1234,
			"average_try": 1.1459
		}
	],
	"last_updated": "Tue Oct 18 21:45:13 2022"
}