{
	"problems": [
		{
			"id": 11385,
			"level": 22,
			"level_locked": 0,
			"solvable": 1,
			"title": "\uc53d\ud06c\uc2a4\ubab0",
			"solved_count": 187,
			"average_try": 6.5187
		},
		{
			"id": 13926,
			"level": 21,
			"level_locked": 0,
			"solvable": 1,
			"title": "gcd(n, k) = 1",
			"solved_count": 314,
			"average_try": 3.3631
		},
		{
			"id": 17633,
			"level": 22,
			"level_locked": 0,
			"solvable": 1,
			"title": "\uc81c\uacf1\uc218\uc758 \ud569 (More Huge)",
			"solved_count": 160,
			"average_try": 3.8063
		},
		{
			"id": 9267,
			"level": 21,
			"level_locked": 0,
			"solvable": 1,
			"title": "A+B",
			"solved_count": 120,
			"average_try": 10.475
		},
		{
			"id": 9237,
			"level": 6,
			"level_locked": 0,
			"solvable": 1,
			"title": "\uc774\uc7a5\ub2d8 \ucd08\ub300",
			"solved_count": 2406,
			"average_try": 1.5781
		},
		{
			"id": 17372,
			"level": 24,
			"level_locked": 0,
			"solvable": 1,
			"title": "\ud53c\ubcf4\ub098\uce58 \uc218\uc758 \ucd5c\ub300\uacf5\uc57d\uc218\uc758 \ud569",
			"solved_count": 56,
			"average_try": 1.6964
		},
		{
			"id": 1059,
			"level": 6,
			"level_locked": 0,
			"solvable": 1,
			"title": "\uc88b\uc740 \uad6c\uac04",
			"solved_count": 2690,
			"average_try": 3.7405
		},
		{
			"id": 14490,
			"level": 6,
			"level_locked": 0,
			"solvable": 1,
			"title": "\ubc31\ub300\uc5f4",
			"solved_count": 2429,
			"average_try": 1.3853
		},
		{
			"id": 13015,
			"level": 6,
			"level_locked": 0,
			"solvable": 1,
			"title": "\ubcc4 \ucc0d\uae30 - 23",
			"solved_count": 1574,
			"average_try": 1.5184
		},
		{
			"id": 1312,
			"level": 6,
			"level_locked": 0,
			"solvable": 1,
			"title": "\uc18c\uc218",
			"solved_count": 1735,
			"average_try": 2.8161
		}
	],
	"last_updated": "Tue Aug  2 21:39:22 2022"
}