{
	"problems": [
		{
			"id": 8718,
			"level": 2,
			"level_locked": 0,
			"solvable": 1,
			"title": "Ba\u0142wanek",
			"solved_count": 828,
			"average_try": 2.4674
		},
		{
			"id": 16099,
			"level": 1,
			"level_locked": 0,
			"solvable": 1,
			"title": "Larger Sport Facility",
			"solved_count": 144,
			"average_try": 1.7014
		},
		{
			"id": 1362,
			"level": 4,
			"level_locked": 0,
			"solvable": 1,
			"title": "\ud3ab",
			"solved_count": 584,
			"average_try": 4.0976
		},
		{
			"id": 21591,
			"level": 2,
			"level_locked": 0,
			"solvable": 1,
			"title": "Laptop Sticker",
			"solved_count": 785,
			"average_try": 1.3758
		},
		{
			"id": 15080,
			"level": 2,
			"level_locked": 0,
			"solvable": 1,
			"title": "Every Second Counts",
			"solved_count": 834,
			"average_try": 1.6775
		},
		{
			"id": 9657,
			"level": 8,
			"level_locked": 0,
			"solvable": 1,
			"title": "\ub3cc \uac8c\uc784 3",
			"solved_count": 2825,
			"average_try": 2.0998
		},
		{
			"id": 3765,
			"level": 2,
			"level_locked": 0,
			"solvable": 1,
			"title": "Celebrity jeopardy",
			"solved_count": 143,
			"average_try": 1.5315
		},
		{
			"id": 22015,
			"level": 2,
			"level_locked": 0,
			"solvable": 1,
			"title": "\u91d1\u5e73\u7cd6 (Konpeito)",
			"solved_count": 701,
			"average_try": 1.1783
		},
		{
			"id": 24263,
			"level": 2,
			"level_locked": 0,
			"solvable": 1,
			"title": "\uc54c\uace0\ub9ac\uc998 \uc218\uc5c5 - \uc54c\uace0\ub9ac\uc998\uc758 \uc218\ud589 \uc2dc\uac04 2",
			"solved_count": 594,
			"average_try": 1.1313
		},
		{
			"id": 16693,
			"level": 2,
			"level_locked": 0,
			"solvable": 1,
			"title": "Pizza Deal",
			"solved_count": 836,
			"average_try": 2.1184
		}
	],
	"last_updated": "Sun Nov 13 21:38:46 2022"
}